petsc4py-stubs/__init__.pyi
petsc4py-stubs/__main__.pyi
petsc4py-stubs/py.typed
petsc4py-stubs/typing.pyi
petsc4py-stubs/PETSc/AO.pyi
petsc4py-stubs/PETSc/Comm.pyi
petsc4py-stubs/PETSc/Const.pyi
petsc4py-stubs/PETSc/DM.pyi
petsc4py-stubs/PETSc/DMComposite.pyi
petsc4py-stubs/PETSc/DMDA.pyi
petsc4py-stubs/PETSc/DMLabel.pyi
petsc4py-stubs/PETSc/DMPlex.pyi
petsc4py-stubs/PETSc/DMShell.pyi
petsc4py-stubs/PETSc/DMStag.pyi
petsc4py-stubs/PETSc/DMSwarm.pyi
petsc4py-stubs/PETSc/DMUtils.pyi
petsc4py-stubs/PETSc/DS.pyi
petsc4py-stubs/PETSc/DT.pyi
petsc4py-stubs/PETSc/Device.pyi
petsc4py-stubs/PETSc/Error.pyi
petsc4py-stubs/PETSc/FE.pyi
petsc4py-stubs/PETSc/IS.pyi
petsc4py-stubs/PETSc/KSP.pyi
petsc4py-stubs/PETSc/Log.pyi
petsc4py-stubs/PETSc/Mat.pyi
petsc4py-stubs/PETSc/MatPartitioning.pyi
petsc4py-stubs/PETSc/Object.pyi
petsc4py-stubs/PETSc/Options.pyi
petsc4py-stubs/PETSc/PC.pyi
petsc4py-stubs/PETSc/Partitioner.pyi
petsc4py-stubs/PETSc/Random.pyi
petsc4py-stubs/PETSc/Regressor.pyi
petsc4py-stubs/PETSc/SF.pyi
petsc4py-stubs/PETSc/SNES.pyi
petsc4py-stubs/PETSc/Scatter.pyi
petsc4py-stubs/PETSc/Section.pyi
petsc4py-stubs/PETSc/Space.pyi
petsc4py-stubs/PETSc/Sys.pyi
petsc4py-stubs/PETSc/TAO.pyi
petsc4py-stubs/PETSc/TS.pyi
petsc4py-stubs/PETSc/Vec.pyi
petsc4py-stubs/PETSc/Viewer.pyi
petsc4py-stubs/PETSc/__init__.pyi
petsc4py-stubs/lib/__init__.pyi
petsc4py_stubs-0.1.8.dist-info/METADATA
petsc4py_stubs-0.1.8.dist-info/WHEEL
petsc4py_stubs-0.1.8.dist-info/licenses/LICENSE
petsc4py_stubs-0.1.8.dist-info/RECORD
